{
  "session_start": "2025-10-16T17:13:52.586100",
  "groups_of_three": [
    {
      "group_number": 1,
      "cubes": [
        {
          "color": "blue",
          "face_name": "Direita",
          "individual_time": 0.061599016189575195,
          "timestamp": "2025-10-16T17:13:23.032069"
        },
        {
          "color": "red",
          "face_name": "Encima",
          "individual_time": 0.09296202659606934,
          "timestamp": "2025-10-16T17:13:24.046497"
        },
        {
          "color": "green",
          "face_name": "Esquerda",
          "individual_time": 0.2819952964782715,
          "timestamp": "2025-10-16T17:13:24.332233"
        }
      ],
      "total_group_time": 0.436556339263916,
      "timestamp": "2025-10-16T17:13:24.332246"
    },
    {
      "group_number": 2,
      "cubes": [
        {
          "color": "blue",
          "face_name": "Direita",
          "individual_time": 0.4191725254058838,
          "timestamp": "2025-10-16T17:13:24.759732"
        },
        {
          "color": "red",
          "face_name": "Encima",
          "individual_time": 0.4391779899597168,
          "timestamp": "2025-10-16T17:13:27.075307"
        },
        {
          "color": "white",
          "face_name": "Frente",
          "individual_time": 0.06178760528564453,
          "timestamp": "2025-10-16T17:13:30.671993"
        }
      ],
      "total_group_time": 0.9201381206512451,
      "timestamp": "2025-10-16T17:13:30.672006"
    },
    {
      "group_number": 3,
      "cubes": [
        {
          "color": "white",
          "face_name": "Frente",
          "individual_time": 0.24928021430969238,
          "timestamp": "2025-10-16T17:13:31.126620"
        },
        {
          "color": "blue",
          "face_name": "Direita",
          "individual_time": 1.178325891494751,
          "timestamp": "2025-10-16T17:13:41.723920"
        },
        {
          "color": "yellow",
          "face_name": "Atras",
          "individual_time": 0.12334704399108887,
          "timestamp": "2025-10-16T17:13:42.341523"
        }
      ],
      "total_group_time": 1.5509531497955322,
      "timestamp": "2025-10-16T17:13:42.341533"
    },
    {
      "group_number": 4,
      "cubes": [
        {
          "color": "blue",
          "face_name": "Direita",
          "individual_time": 1.9102551937103271,
          "timestamp": "2025-10-16T17:13:44.250375"
        },
        {
          "color": "red",
          "face_name": "Encima",
          "individual_time": 0.1893157958984375,
          "timestamp": "2025-10-16T17:13:45.683610"
        },
        {
          "color": "white",
          "face_name": "Frente",
          "individual_time": 0.1872119903564453,
          "timestamp": "2025-10-16T17:13:50.225329"
        }
      ],
      "total_group_time": 2.28678297996521,
      "timestamp": "2025-10-16T17:13:50.225339"
    },
    {
      "group_number": 5,
      "cubes": [
        {
          "color": "blue",
          "face_name": "Direita",
          "individual_time": 0.20003819465637207,
          "timestamp": "2025-10-16T17:13:50.424840"
        },
        {
          "color": "white",
          "face_name": "Frente",
          "individual_time": 0.06280088424682617,
          "timestamp": "2025-10-16T17:13:50.490654"
        },
        {
          "color": "yellow",
          "face_name": "Atras",
          "individual_time": 0.12658381462097168,
          "timestamp": "2025-10-16T17:13:51.510292"
        }
      ],
      "total_group_time": 0.3894228935241699,
      "timestamp": "2025-10-16T17:13:51.510303"
    },
    {
      "group_number": 6,
      "cubes": [
        {
          "color": "white",
          "face_name": "Frente",
          "individual_time": 0.5757946968078613,
          "timestamp": "2025-10-16T17:13:52.152820"
        },
        {
          "color": "blue",
          "face_name": "Direita",
          "individual_time": 0.12592267990112305,
          "timestamp": "2025-10-16T17:13:52.276242"
        },
        {
          "color": "yellow",
          "face_name": "Atras",
          "individual_time": 0.30838561058044434,
          "timestamp": "2025-10-16T17:13:52.585407"
        }
      ],
      "total_group_time": 1.0101029872894287,
      "timestamp": "2025-10-16T17:13:52.585418"
    }
  ],
  "total_groups": 6
}